README.rst
setup.py
mw_wechatpay/__init__.py
mw_wechatpay/pay_client.py
mw_wechatpay/rsa_crypt_util.py
mw_wechatpay/time_util.py
mw_wechatpay/wecatpay_certificates.py
mw_wechatpay.egg-info/PKG-INFO
mw_wechatpay.egg-info/SOURCES.txt
mw_wechatpay.egg-info/dependency_links.txt
mw_wechatpay.egg-info/not-zip-safe
mw_wechatpay.egg-info/top_level.txt